request_logger/__init__.py
request_logger/cli/__init__.py
request_logger/web/app.py
request_logger/web/main.py
request_logger/web/static/css/styles.css
request_logger/web/static/js/scripts.js
request_logger/web/templates/base.html
request_logger/web/templates/index.html
request_logger/web/templates/modify_form.html
request_logger/web/templates/replay_result.html
request_logger/web/templates/request_detail.html
request_logger/web/templates/request_list.html
py_requests_logger-0.1.0.dist-info/METADATA
py_requests_logger-0.1.0.dist-info/WHEEL
py_requests_logger-0.1.0.dist-info/entry_points.txt
py_requests_logger-0.1.0.dist-info/top_level.txt
py_requests_logger-0.1.0.dist-info/RECORD
