Metadata-Version: 2.2
Name: py-requests-logger
Version: 0.1.0
Summary: A Python package for logging and replaying HTTP requests
Author-email: Ashish Subedi <ashish@asubedi.com.np>
License: MIT
Classifier: Programming Language :: Python :: 3.8
Classifier: Programming Language :: Python :: 3.9
Classifier: Programming Language :: Python :: 3.10
Classifier: Programming Language :: Python :: 3.11
Classifier: Programming Language :: Python :: 3.12
Classifier: License :: OSI Approved :: MIT License
Classifier: Operating System :: OS Independent
Requires-Python: >=3.8
Requires-Dist: requests>=2.32.3
Requires-Dist: boto3>=1.36.7
Requires-Dist: python-multipart>=0.0.20
Provides-Extra: postgres
Requires-Dist: psycopg2>=2.8.6; extra == "postgres"
Provides-Extra: web
Requires-Dist: fastapi>=0.115.7; extra == "web"
Requires-Dist: uvicorn>=0.33.0; extra == "web"
Requires-Dist: jinja2>=3.1.5; extra == "web"
